setup.py
hello_word/Connection.py
hello_word/cnames.py
hello_word/test.py
hello_word.egg-info/PKG-INFO
hello_word.egg-info/SOURCES.txt
hello_word.egg-info/dependency_links.txt
hello_word.egg-info/not-zip-safe
hello_word.egg-info/requires.txt
hello_word.egg-info/top_level.txt