Metadata-Version: 1.0
Name: hello-word
Version: 0.1.3
Summary: Hello Word Project
Home-page: https://gitlab.com/arcesium/private/users/guptmani/hello_word
Author: guptmani
Author-email: guptmani@arcesium.com
License: MIT
Platform: UNKNOWN
